Metadata-Version: 2.1
Name: hl7lib
Version: 1.0.0
Summary: HL7 message parser
Home-page: https://github.com/norlowski/HL7py
Author: fatryst
Author-email: fatryst@gmail.com
License: MIT
Keywords: hl7 parsing
Platform: UNKNOWN
License-File: LICENSE
